{
  "feature_idx": 5927,
  "stats": {
    "sampling": {
      "method": "sequential_from_start",
      "description": "First N tokens in corpus order (not random)",
      "tokens_scanned": 100000,
      "corpus_coverage": 0.0019
    },
    "total_activations": 21,
    "mean_when_active": 0.06464276994977679,
    "max_activation": 0.2054443359375,
    "std_when_active": 0.050547833304504027,
    "activation_rate": 0.00021
  },
  "top_tokens": {
    "sampling": {
      "method": "sequential_from_start",
      "description": "First N activations in corpus order (not random)",
      "activations_collected": 7483,
      "tokens_scanned": 51702947,
      "corpus_coverage": 1.0
    },
    "top_tokens": [
      {
        "token": " Washington",
        "count": 511,
        "mean_activation": 0.14022555416577484
      },
      {
        "token": " ago",
        "count": 444,
        "mean_activation": 0.026474342689857825
      },
      {
        "token": " 2018",
        "count": 241,
        "mean_activation": 0.0998172997439056
      },
      {
        "token": " 2016",
        "count": 237,
        "mean_activation": 0.10954754664425105
      },
      {
        "token": " 2020",
        "count": 214,
        "mean_activation": 0.06698037976416472
      },
      {
        "token": " 2017",
        "count": 212,
        "mean_activation": 0.12624862958800118
      },
      {
        "token": " 2014",
        "count": 210,
        "mean_activation": 0.12841280982607886
      },
      {
        "token": " 2019",
        "count": 210,
        "mean_activation": 0.06523321242559524
      },
      {
        "token": " 2015",
        "count": 203,
        "mean_activation": 0.1126048271291949
      },
      {
        "token": "s",
        "count": 187,
        "mean_activation": 0.047309345102565174
      }
    ]
  },
  "top_activations": {
    "sampling": {
      "method": "top_by_activation",
      "description": "Strongest activations within scanned tokens (not full corpus)",
      "top_k_requested": 10,
      "n_found": 10,
      "activations_scanned": 7483,
      "tokens_scanned": 51702947,
      "corpus_coverage": 1.0
    },
    "activations": [
      {
        "context": "...fair with started in** 2013** when the OG capital ...",
        "active_token": " 2013",
        "activation": 0.22900390625,
        "review_id": "hBu7V-VffnGwUI2e8KeZ7A",
        "position": 19
      },
      {
        "context": "...as been around since** 2013** yet I've never tried...",
        "active_token": " 2013",
        "activation": 0.2230224609375,
        "review_id": "cSVojTFEBAu-TTXhe4Ng3A",
        "position": 5
      },
      {
        "context": "...ed into Tennessee in** 2003**. Anyway, it's flavor...",
        "active_token": " 2003",
        "activation": 0.220947265625,
        "review_id": "jyQo7Enl5-jb7GlSrldNAg",
        "position": 50
      },
      {
        "context": "...e Se\u00c3\u00b1or Tequilas in** 2013** for my sister's grad...",
        "active_token": " 2013",
        "activation": 0.216796875,
        "review_id": "_2SGFBweIIx9uZVxs_MWkQ",
        "position": 33
      },
      {
        "context": "... years, beginning in** 2008**.  The outside seatin...",
        "active_token": " 2008",
        "activation": 0.21630859375,
        "review_id": "JDN8Sy-cFRTasgayfmt2zA",
        "position": 21
      },
      {
        "context": "...orth End starting in** 2005** brought in swanky ea...",
        "active_token": " 2005",
        "activation": 0.2152099609375,
        "review_id": "SDoRib2E-I0-ER8Unka0ig",
        "position": 35
      },
      {
        "context": "... first moved here in** 2005**... I remember them s...",
        "active_token": " 2005",
        "activation": 0.2137451171875,
        "review_id": "guJzqM8k80BNqiMasQai-w",
        "position": 16
      },
      {
        "context": "...ved to Isla Vista in** 2005** to start at UCSB, I ...",
        "active_token": " 2005",
        "activation": 0.211181640625,
        "review_id": "2kOyyFK_EwbrTyZzy68cZg",
        "position": 16
      },
      {
        "context": "...e moved to Tucson in** 2012**.  It's not much to l...",
        "active_token": " 2012",
        "activation": 0.2095947265625,
        "review_id": "WUCu4N9r420dMxDvj4rNKQ",
        "position": 54
      },
      {
        "context": "...e his first visit in** 2004**. Tonight we were und...",
        "active_token": " 2004",
        "activation": 0.209228515625,
        "review_id": "mJhiSeyAyidtZKu46Ge1Bw",
        "position": 18
      }
    ]
  },
  "ngram_analysis": {
    "feature_idx": 5927,
    "sampling": {
      "method": "top_by_activation",
      "description": "Top N activations by strength (not random)",
      "n_requested": 500,
      "n_found": 500,
      "tokens_scanned": 51702947,
      "corpus_coverage": 1.0,
      "activation_range": {
        "min": 0.1708,
        "max": 0.229,
        "mean": 0.1846
      }
    },
    "n_contexts_analyzed": 500,
    "context_window": 5,
    "ngrams": {
      "2grams": [
        {
          "ngram": [
            " back",
            " in"
          ],
          "ngram_str": " back in",
          "count": 50,
          "percent": 10.0
        },
        {
          "ngram": [
            ".",
            " "
          ],
          "ngram_str": ". ",
          "count": 43,
          "percent": 8.6
        },
        {
          "ngram": [
            "\u00c4",
            "\u012c"
          ],
          "ngram_str": "\u00c4\u012c",
          "count": 31,
          "percent": 6.2
        },
        {
          "ngram": [
            ",",
            " and"
          ],
          "ngram_str": ", and",
          "count": 31,
          "percent": 6.2
        },
        {
          "ngram": [
            " here",
            " in"
          ],
          "ngram_str": " here in",
          "count": 30,
          "percent": 6.0
        },
        {
          "ngram": [
            " in",
            " 2014"
          ],
          "ngram_str": " in 2014",
          "count": 29,
          "percent": 5.8
        },
        {
          "ngram": [
            " moved",
            " to"
          ],
          "ngram_str": " moved to",
          "count": 26,
          "percent": 5.2
        },
        {
          "ngram": [
            " in",
            " 2009"
          ],
          "ngram_str": " in 2009",
          "count": 26,
          "percent": 5.2
        },
        {
          "ngram": [
            " in",
            " 2012"
          ],
          "ngram_str": " in 2012",
          "count": 23,
          "percent": 4.6
        },
        {
          "ngram": [
            ".",
            " I"
          ],
          "ngram_str": ". I",
          "count": 22,
          "percent": 4.4
        },
        {
          "ngram": [
            " I",
            " moved"
          ],
          "ngram_str": " I moved",
          "count": 22,
          "percent": 4.4
        },
        {
          "ngram": [
            " and",
            " I"
          ],
          "ngram_str": " and I",
          "count": 22,
          "percent": 4.4
        },
        {
          "ngram": [
            " in",
            " 2005"
          ],
          "ngram_str": " in 2005",
          "count": 21,
          "percent": 4.2
        },
        {
          "ngram": [
            " in",
            " 2008"
          ],
          "ngram_str": " in 2008",
          "count": 20,
          "percent": 4.0
        },
        {
          "ngram": [
            " in",
            " 2010"
          ],
          "ngram_str": " in 2010",
          "count": 20,
          "percent": 4.0
        }
      ],
      "3grams": [
        {
          "ngram": [
            "\u012c",
            "\u00c4",
            "\u012c"
          ],
          "ngram_str": "\u012c\u00c4\u012c",
          "count": 15,
          "percent": 3.0
        },
        {
          "ngram": [
            ".",
            " ",
            " I"
          ],
          "ngram_str": ".  I",
          "count": 13,
          "percent": 2.6
        },
        {
          "ngram": [
            " I",
            " moved",
            " to"
          ],
          "ngram_str": " I moved to",
          "count": 11,
          "percent": 2.2
        },
        {
          "ngram": [
            " in",
            " 2008",
            "."
          ],
          "ngram_str": " in 2008.",
          "count": 9,
          "percent": 1.8
        },
        {
          "ngram": [
            "\u00c4",
            "\u012c",
            "\u00c4"
          ],
          "ngram_str": "\u00c4\u012c\u00c4",
          "count": 9,
          "percent": 1.8
        },
        {
          "ngram": [
            " in",
            " 2014",
            " and"
          ],
          "ngram_str": " in 2014 and",
          "count": 9,
          "percent": 1.8
        },
        {
          "ngram": [
            " to",
            " Tucson",
            " in"
          ],
          "ngram_str": " to Tucson in",
          "count": 8,
          "percent": 1.6
        },
        {
          "ngram": [
            " in",
            " 2005",
            "."
          ],
          "ngram_str": " in 2005.",
          "count": 8,
          "percent": 1.6
        },
        {
          "ngram": [
            " 2013",
            ".",
            " "
          ],
          "ngram_str": " 2013. ",
          "count": 8,
          "percent": 1.6
        },
        {
          "ngram": [
            ".",
            " \u00c4",
            "\u012c"
          ],
          "ngram_str": ". \u00c4\u012c",
          "count": 8,
          "percent": 1.6
        },
        {
          "ngram": [
            " in",
            " 2009",
            "."
          ],
          "ngram_str": " in 2009.",
          "count": 8,
          "percent": 1.6
        },
        {
          "ngram": [
            " moved",
            " here",
            " in"
          ],
          "ngram_str": " moved here in",
          "count": 7,
          "percent": 1.4
        },
        {
          "ngram": [
            " in",
            " 2012",
            ","
          ],
          "ngram_str": " in 2012,",
          "count": 7,
          "percent": 1.4
        },
        {
          "ngram": [
            " in",
            " 2009",
            ","
          ],
          "ngram_str": " in 2009,",
          "count": 7,
          "percent": 1.4
        },
        {
          "ngram": [
            ".",
            "\u00c4",
            "\u012c"
          ],
          "ngram_str": ".\u00c4\u012c",
          "count": 7,
          "percent": 1.4
        }
      ],
      "4grams": [
        {
          "ngram": [
            "\u00c4",
            "\u012c",
            "\u00c4",
            "\u012c"
          ],
          "ngram_str": "\u00c4\u012c\u00c4\u012c",
          "count": 9,
          "percent": 1.8
        },
        {
          "ngram": [
            " moved",
            " to",
            " Tucson",
            " in"
          ],
          "ngram_str": " moved to Tucson in",
          "count": 6,
          "percent": 1.2
        },
        {
          "ngram": [
            ".",
            " \u00c4",
            "\u012c",
            "\u00c4"
          ],
          "ngram_str": ". \u00c4\u012c\u00c4",
          "count": 6,
          "percent": 1.2
        },
        {
          "ngram": [
            " \u00c4",
            "\u012c",
            "\u00c4",
            "\u012c"
          ],
          "ngram_str": " \u00c4\u012c\u00c4\u012c",
          "count": 6,
          "percent": 1.2
        },
        {
          "ngram": [
            ".",
            "\u00c4",
            "\u012c",
            "\u00c4"
          ],
          "ngram_str": ".\u00c4\u012c\u00c4",
          "count": 6,
          "percent": 1.2
        },
        {
          "ngram": [
            " 2013",
            ".",
            " ",
            " I"
          ],
          "ngram_str": " 2013.  I",
          "count": 5,
          "percent": 1.0
        },
        {
          "ngram": [
            " been",
            " coming",
            " here",
            " since"
          ],
          "ngram_str": " been coming here since",
          "count": 5,
          "percent": 1.0
        },
        {
          "ngram": [
            " to",
            " this",
            " place",
            " since"
          ],
          "ngram_str": " to this place since",
          "count": 4,
          "percent": 0.8
        },
        {
          "ngram": [
            " in",
            " 2015",
            ".",
            " "
          ],
          "ngram_str": " in 2015. ",
          "count": 4,
          "percent": 0.8
        },
        {
          "ngram": [
            " I",
            " moved",
            " here",
            " in"
          ],
          "ngram_str": " I moved here in",
          "count": 4,
          "percent": 0.8
        },
        {
          "ngram": [
            " since",
            " moving",
            " here",
            " in"
          ],
          "ngram_str": " since moving here in",
          "count": 4,
          "percent": 0.8
        },
        {
          "ngram": [
            " for",
            " the",
            " first",
            " time"
          ],
          "ngram_str": " for the first time",
          "count": 4,
          "percent": 0.8
        },
        {
          "ngram": [
            ".",
            " The",
            " food",
            " is"
          ],
          "ngram_str": ". The food is",
          "count": 3,
          "percent": 0.6
        },
        {
          "ngram": [
            " since",
            " it",
            " opened",
            " in"
          ],
          "ngram_str": " since it opened in",
          "count": 3,
          "percent": 0.6
        },
        {
          "ngram": [
            " moved",
            " to",
            " Tampa",
            " in"
          ],
          "ngram_str": " moved to Tampa in",
          "count": 3,
          "percent": 0.6
        }
      ]
    }
  },
  "coactivation": {
    "sampling": {
      "method": "sequential_from_start",
      "description": "First N activations in corpus order",
      "activations_sampled": 7483,
      "tokens_scanned": 51702947,
      "corpus_coverage": 1.0
    },
    "coactivated_features": [
      {
        "feature_idx": 6049,
        "count": 5145,
        "percent": 68.76
      },
      {
        "feature_idx": 17175,
        "count": 5094,
        "percent": 68.07
      },
      {
        "feature_idx": 2079,
        "count": 4214,
        "percent": 56.31
      },
      {
        "feature_idx": 18099,
        "count": 3982,
        "percent": 53.21
      },
      {
        "feature_idx": 12525,
        "count": 3587,
        "percent": 47.94
      },
      {
        "feature_idx": 12508,
        "count": 3072,
        "percent": 41.05
      },
      {
        "feature_idx": 17947,
        "count": 3035,
        "percent": 40.56
      },
      {
        "feature_idx": 20172,
        "count": 2743,
        "percent": 36.66
      },
      {
        "feature_idx": 13799,
        "count": 2687,
        "percent": 35.91
      },
      {
        "feature_idx": 21472,
        "count": 2645,
        "percent": 35.35
      },
      {
        "feature_idx": 24129,
        "count": 2531,
        "percent": 33.82
      },
      {
        "feature_idx": 11763,
        "count": 2031,
        "percent": 27.14
      },
      {
        "feature_idx": 19995,
        "count": 1987,
        "percent": 26.55
      },
      {
        "feature_idx": 18704,
        "count": 1955,
        "percent": 26.13
      },
      {
        "feature_idx": 22894,
        "count": 1898,
        "percent": 25.36
      },
      {
        "feature_idx": 13586,
        "count": 1874,
        "percent": 25.04
      },
      {
        "feature_idx": 2108,
        "count": 1808,
        "percent": 24.16
      },
      {
        "feature_idx": 5496,
        "count": 1733,
        "percent": 23.16
      },
      {
        "feature_idx": 24446,
        "count": 1696,
        "percent": 22.66
      },
      {
        "feature_idx": 1227,
        "count": 1606,
        "percent": 21.46
      }
    ]
  },
  "position_distribution": {
    "sampling": {
      "method": "sequential_from_start",
      "description": "First N activations in corpus order",
      "activations_sampled": 7483,
      "tokens_scanned": 51702947,
      "corpus_coverage": 1.0
    },
    "bins": [
      {
        "range": "0-20%",
        "label": "early",
        "count": 3655,
        "percent": 48.84
      },
      {
        "range": "20-40%",
        "label": "early-mid",
        "count": 1326,
        "percent": 17.72
      },
      {
        "range": "40-60%",
        "label": "middle",
        "count": 754,
        "percent": 10.08
      },
      {
        "range": "60-80%",
        "label": "late-mid",
        "count": 722,
        "percent": 9.65
      },
      {
        "range": "80-100%",
        "label": "late",
        "count": 1026,
        "percent": 13.71
      }
    ],
    "mean_position": 0.3372,
    "std_position": 0.3092
  },
  "activation_distribution": {
    "sampling": {
      "method": "sequential_from_start",
      "description": "First N tokens in corpus order",
      "tokens_scanned": 100000,
      "n_activations": 21,
      "corpus_coverage": 0.0019
    },
    "percentiles": {
      "p10": 0.0266,
      "p25": 0.0287,
      "p50": 0.0395,
      "p75": 0.0938,
      "p90": 0.1334,
      "p95": 0.1471,
      "p99": 0.1938
    },
    "skewness": 1.2919,
    "kurtosis": 0.6593,
    "min": 0.0166,
    "max": 0.2054,
    "mean": 0.0646,
    "std": 0.0505
  },
  "top_token_contexts": {
    "sampling": {
      "method": "sequential_from_start",
      "description": "First N tokens in corpus order, top activations per token",
      "tokens_scanned": 100000,
      "corpus_coverage": 0.0019,
      "activations_found": 21,
      "unique_tokens_found": 16
    },
    "tokens": [
      {
        "token": " Houston",
        "count": 4,
        "mean_activation": 0.029
      },
      {
        "token": " 2015",
        "count": 2,
        "mean_activation": 0.1089
      },
      {
        "token": "s",
        "count": 2,
        "mean_activation": 0.0427
      },
      {
        "token": " Washington",
        "count": 1,
        "mean_activation": 0.1334
      },
      {
        "token": " 1988",
        "count": 1,
        "mean_activation": 0.1155
      },
      {
        "token": " year",
        "count": 1,
        "mean_activation": 0.0287
      },
      {
        "token": " 2016",
        "count": 1,
        "mean_activation": 0.1471
      },
      {
        "token": " 10",
        "count": 1,
        "mean_activation": 0.0166
      },
      {
        "token": " 90",
        "count": 1,
        "mean_activation": 0.0421
      },
      {
        "token": "uded",
        "count": 1,
        "mean_activation": 0.0395
      }
    ]
  }
}