{
  "feature_idx": 12495,
  "stats": {
    "sampling": {
      "method": "sequential_from_start",
      "description": "First N tokens in corpus order (not random)",
      "tokens_scanned": 100000,
      "corpus_coverage": 0.0019
    },
    "total_activations": 15,
    "mean_when_active": 0.10108642578125,
    "max_activation": 0.244384765625,
    "std_when_active": 0.07265553730440787,
    "activation_rate": 0.00015
  },
  "top_tokens": {
    "sampling": {
      "method": "sequential_from_start",
      "description": "First N activations in corpus order (not random)",
      "activations_collected": 9455,
      "tokens_scanned": 51702947,
      "corpus_coverage": 1.0
    },
    "top_tokens": [
      {
        "token": " away",
        "count": 3156,
        "mean_activation": 0.14687196081279952
      },
      {
        "token": " out",
        "count": 2460,
        "mean_activation": 0.0744262044022723
      },
      {
        "token": " off",
        "count": 1340,
        "mean_activation": 0.09382472251778218
      },
      {
        "token": " back",
        "count": 523,
        "mean_activation": 0.05241216072388862
      },
      {
        "token": " by",
        "count": 402,
        "mean_activation": 0.036747605053346545
      },
      {
        "token": " of",
        "count": 375,
        "mean_activation": 0.049834228515625
      },
      {
        "token": " home",
        "count": 249,
        "mean_activation": 0.04054346046294553
      },
      {
        "token": " from",
        "count": 100,
        "mean_activation": 0.04535125732421875
      },
      {
        "token": " left",
        "count": 98,
        "mean_activation": 0.028651412652463328
      },
      {
        "token": " there",
        "count": 85,
        "mean_activation": 0.026543381634880514
      }
    ]
  },
  "top_activations": {
    "sampling": {
      "method": "top_by_activation",
      "description": "Strongest activations within scanned tokens (not full corpus)",
      "top_k_requested": 10,
      "n_found": 10,
      "activations_scanned": 9455,
      "tokens_scanned": 51702947,
      "corpus_coverage": 1.0
    },
    "activations": [
      {
        "context": "...y Buddy!\" and walked** away**!  \\n\\nUltimately, it's...",
        "active_token": " away",
        "activation": 0.27197265625,
        "review_id": "wIypnCC3eUGKtvHgGXS4VA",
        "position": 382
      },
      {
        "context": "...ippity way and walks** away**. No apologies, nothi...",
        "active_token": " away",
        "activation": 0.269775390625,
        "review_id": "yjRJBrsUpwihb7zBEfBO4g",
        "position": 318
      },
      {
        "context": "...\"too bad\" and walked** away** as we were still try...",
        "active_token": " away",
        "activation": 0.2685546875,
        "review_id": "ngPcOkeyFm8FCAnfBAgxxA",
        "position": 249
      },
      {
        "context": "... says \"OK\" and walks** away**.  He was not even in...",
        "active_token": " away",
        "activation": 0.267578125,
        "review_id": "RsJH-tghCRphEbSqcQs-ow",
        "position": 614
      },
      {
        "context": "...ked at us and walked** away**. Don't bother going.",
        "active_token": " away",
        "activation": 0.267333984375,
        "review_id": "O285R4l3EBxvJoB7IlAOwQ",
        "position": 25
      },
      {
        "context": "...uld' and then walked** away**.  We had some 'regul...",
        "active_token": " away",
        "activation": 0.266845703125,
        "review_id": "VntKwIOxJmGF-I1aOCLqWA",
        "position": 101
      },
      {
        "context": "...en proceeded to walk** away**! No \"Oh, I'm sorry f...",
        "active_token": " away",
        "activation": 0.266845703125,
        "review_id": "HyOrhWHfzRN5FspkMnfTSA",
        "position": 179
      },
      {
        "context": "... a table\" and walked** away**.  When we finally di...",
        "active_token": " away",
        "activation": 0.265380859375,
        "review_id": "p2Kd5Wttt_nzhXGUAY-HTA",
        "position": 163
      },
      {
        "context": "..., hang on\" and walks** away**. So she goes to seat...",
        "active_token": " away",
        "activation": 0.2646484375,
        "review_id": "OWxCN91y7lbjpVqOSPaZmQ",
        "position": 162
      },
      {
        "context": "...itress, \"....\" walks** away**. \\n\\n6 minutes later, ...",
        "active_token": " away",
        "activation": 0.264404296875,
        "review_id": "ErSVmoRr5tXu_6VSt3MOPw",
        "position": 185
      }
    ]
  },
  "ngram_analysis": {
    "feature_idx": 12495,
    "sampling": {
      "method": "top_by_activation",
      "description": "Top N activations by strength (not random)",
      "n_requested": 500,
      "n_found": 500,
      "tokens_scanned": 51702947,
      "corpus_coverage": 1.0,
      "activation_range": {
        "min": 0.2395,
        "max": 0.272,
        "mean": 0.249
      }
    },
    "n_contexts_analyzed": 500,
    "context_window": 5,
    "ngrams": {
      "2grams": [
        {
          "ngram": [
            " walked",
            " away"
          ],
          "ngram_str": " walked away",
          "count": 414,
          "percent": 82.8
        },
        {
          "ngram": [
            " away",
            "."
          ],
          "ngram_str": " away.",
          "count": 300,
          "percent": 60.0
        },
        {
          "ngram": [
            " and",
            " walked"
          ],
          "ngram_str": " and walked",
          "count": 273,
          "percent": 54.6
        },
        {
          "ngram": [
            ".",
            " "
          ],
          "ngram_str": ". ",
          "count": 73,
          "percent": 14.6
        },
        {
          "ngram": [
            " walks",
            " away"
          ],
          "ngram_str": " walks away",
          "count": 67,
          "percent": 13.4
        },
        {
          "ngram": [
            "\"",
            " and"
          ],
          "ngram_str": "\" and",
          "count": 59,
          "percent": 11.8
        },
        {
          "ngram": [
            " then",
            " walked"
          ],
          "ngram_str": " then walked",
          "count": 46,
          "percent": 9.2
        },
        {
          "ngram": [
            "\u00c4",
            "\u012c"
          ],
          "ngram_str": "\u00c4\u012c",
          "count": 45,
          "percent": 9.0
        },
        {
          "ngram": [
            " and",
            " walks"
          ],
          "ngram_str": " and walks",
          "count": 44,
          "percent": 8.8
        },
        {
          "ngram": [
            ".",
            " I"
          ],
          "ngram_str": ". I",
          "count": 43,
          "percent": 8.6
        },
        {
          "ngram": [
            " and",
            " then"
          ],
          "ngram_str": " and then",
          "count": 38,
          "percent": 7.6
        },
        {
          "ngram": [
            "\u012c",
            "\u00c4"
          ],
          "ngram_str": "\u012c\u00c4",
          "count": 29,
          "percent": 5.8
        },
        {
          "ngram": [
            " \u00c4",
            "\u012c"
          ],
          "ngram_str": " \u00c4\u012c",
          "count": 27,
          "percent": 5.4
        },
        {
          "ngram": [
            " just",
            " walked"
          ],
          "ngram_str": " just walked",
          "count": 27,
          "percent": 5.4
        },
        {
          "ngram": [
            ",",
            " and"
          ],
          "ngram_str": ", and",
          "count": 26,
          "percent": 5.2
        }
      ],
      "3grams": [
        {
          "ngram": [
            " and",
            " walked",
            " away"
          ],
          "ngram_str": " and walked away",
          "count": 273,
          "percent": 54.6
        },
        {
          "ngram": [
            " walked",
            " away",
            "."
          ],
          "ngram_str": " walked away.",
          "count": 249,
          "percent": 49.8
        },
        {
          "ngram": [
            " away",
            ".",
            " "
          ],
          "ngram_str": " away. ",
          "count": 67,
          "percent": 13.4
        },
        {
          "ngram": [
            " then",
            " walked",
            " away"
          ],
          "ngram_str": " then walked away",
          "count": 46,
          "percent": 9.2
        },
        {
          "ngram": [
            " and",
            " walks",
            " away"
          ],
          "ngram_str": " and walks away",
          "count": 44,
          "percent": 8.8
        },
        {
          "ngram": [
            " away",
            ".",
            " I"
          ],
          "ngram_str": " away. I",
          "count": 41,
          "percent": 8.2
        },
        {
          "ngram": [
            " walks",
            " away",
            "."
          ],
          "ngram_str": " walks away.",
          "count": 40,
          "percent": 8.0
        },
        {
          "ngram": [
            "\"",
            " and",
            " walked"
          ],
          "ngram_str": "\" and walked",
          "count": 38,
          "percent": 7.6
        },
        {
          "ngram": [
            "\u012c",
            "\u00c4",
            "\u012c"
          ],
          "ngram_str": "\u012c\u00c4\u012c",
          "count": 29,
          "percent": 5.8
        },
        {
          "ngram": [
            " just",
            " walked",
            " away"
          ],
          "ngram_str": " just walked away",
          "count": 27,
          "percent": 5.4
        },
        {
          "ngram": [
            " and",
            " then",
            " walked"
          ],
          "ngram_str": " and then walked",
          "count": 21,
          "percent": 4.2
        },
        {
          "ngram": [
            " walked",
            " away",
            ","
          ],
          "ngram_str": " walked away,",
          "count": 20,
          "percent": 4.0
        },
        {
          "ngram": [
            " \u00c4",
            "\u012c",
            "\u00c4"
          ],
          "ngram_str": " \u00c4\u012c\u00c4",
          "count": 19,
          "percent": 3.8
        },
        {
          "ngram": [
            " walked",
            " away",
            " and"
          ],
          "ngram_str": " walked away and",
          "count": 18,
          "percent": 3.6
        },
        {
          "ngram": [
            " away",
            ".",
            " We"
          ],
          "ngram_str": " away. We",
          "count": 17,
          "percent": 3.4
        }
      ],
      "4grams": [
        {
          "ngram": [
            " and",
            " walked",
            " away",
            "."
          ],
          "ngram_str": " and walked away.",
          "count": 177,
          "percent": 35.4
        },
        {
          "ngram": [
            " walked",
            " away",
            ".",
            " "
          ],
          "ngram_str": " walked away. ",
          "count": 56,
          "percent": 11.2
        },
        {
          "ngram": [
            "\"",
            " and",
            " walked",
            " away"
          ],
          "ngram_str": "\" and walked away",
          "count": 38,
          "percent": 7.6
        },
        {
          "ngram": [
            " walked",
            " away",
            ".",
            " I"
          ],
          "ngram_str": " walked away. I",
          "count": 33,
          "percent": 6.6
        },
        {
          "ngram": [
            " and",
            " walks",
            " away",
            "."
          ],
          "ngram_str": " and walks away.",
          "count": 29,
          "percent": 5.8
        },
        {
          "ngram": [
            " then",
            " walked",
            " away",
            "."
          ],
          "ngram_str": " then walked away.",
          "count": 23,
          "percent": 4.6
        },
        {
          "ngram": [
            " and",
            " then",
            " walked",
            " away"
          ],
          "ngram_str": " and then walked away",
          "count": 21,
          "percent": 4.2
        },
        {
          "ngram": [
            " \u00c4",
            "\u012c",
            "\u00c4",
            "\u012c"
          ],
          "ngram_str": " \u00c4\u012c\u00c4\u012c",
          "count": 19,
          "percent": 3.8
        },
        {
          "ngram": [
            " away",
            ".",
            " \u00c4",
            "\u012c"
          ],
          "ngram_str": " away. \u00c4\u012c",
          "count": 16,
          "percent": 3.2
        },
        {
          "ngram": [
            " just",
            " walked",
            " away",
            "."
          ],
          "ngram_str": " just walked away.",
          "count": 16,
          "percent": 3.2
        },
        {
          "ngram": [
            " us",
            " and",
            " walked",
            " away"
          ],
          "ngram_str": " us and walked away",
          "count": 15,
          "percent": 3.0
        },
        {
          "ngram": [
            " walked",
            " away",
            ".",
            " We"
          ],
          "ngram_str": " walked away. We",
          "count": 15,
          "percent": 3.0
        },
        {
          "ngram": [
            " walked",
            " away",
            ".",
            " The"
          ],
          "ngram_str": " walked away. The",
          "count": 13,
          "percent": 2.6
        },
        {
          "ngram": [
            " table",
            " and",
            " walked",
            " away"
          ],
          "ngram_str": " table and walked away",
          "count": 13,
          "percent": 2.6
        },
        {
          "ngram": [
            ".",
            " \u00c4",
            "\u012c",
            "\u00c4"
          ],
          "ngram_str": ". \u00c4\u012c\u00c4",
          "count": 12,
          "percent": 2.4
        }
      ]
    }
  },
  "coactivation": {
    "sampling": {
      "method": "sequential_from_start",
      "description": "First N activations in corpus order",
      "activations_sampled": 9455,
      "tokens_scanned": 51702947,
      "corpus_coverage": 1.0
    },
    "coactivated_features": [
      {
        "feature_idx": 19549,
        "count": 6310,
        "percent": 66.74
      },
      {
        "feature_idx": 21363,
        "count": 5976,
        "percent": 63.2
      },
      {
        "feature_idx": 20172,
        "count": 4902,
        "percent": 51.85
      },
      {
        "feature_idx": 18728,
        "count": 4679,
        "percent": 49.49
      },
      {
        "feature_idx": 10622,
        "count": 4450,
        "percent": 47.07
      },
      {
        "feature_idx": 8665,
        "count": 4049,
        "percent": 42.82
      },
      {
        "feature_idx": 17175,
        "count": 4004,
        "percent": 42.35
      },
      {
        "feature_idx": 22650,
        "count": 3934,
        "percent": 41.61
      },
      {
        "feature_idx": 18704,
        "count": 3800,
        "percent": 40.19
      },
      {
        "feature_idx": 18312,
        "count": 3681,
        "percent": 38.93
      },
      {
        "feature_idx": 16669,
        "count": 3641,
        "percent": 38.51
      },
      {
        "feature_idx": 22894,
        "count": 3493,
        "percent": 36.94
      },
      {
        "feature_idx": 12584,
        "count": 3256,
        "percent": 34.44
      },
      {
        "feature_idx": 21939,
        "count": 3244,
        "percent": 34.31
      },
      {
        "feature_idx": 4197,
        "count": 3219,
        "percent": 34.05
      },
      {
        "feature_idx": 20153,
        "count": 3134,
        "percent": 33.15
      },
      {
        "feature_idx": 5709,
        "count": 3053,
        "percent": 32.29
      },
      {
        "feature_idx": 12867,
        "count": 3043,
        "percent": 32.18
      },
      {
        "feature_idx": 21641,
        "count": 2918,
        "percent": 30.86
      },
      {
        "feature_idx": 3411,
        "count": 2817,
        "percent": 29.79
      }
    ]
  },
  "position_distribution": {
    "sampling": {
      "method": "sequential_from_start",
      "description": "First N activations in corpus order",
      "activations_sampled": 9455,
      "tokens_scanned": 51702947,
      "corpus_coverage": 1.0
    },
    "bins": [
      {
        "range": "0-20%",
        "label": "early",
        "count": 929,
        "percent": 9.83
      },
      {
        "range": "20-40%",
        "label": "early-mid",
        "count": 1693,
        "percent": 17.91
      },
      {
        "range": "40-60%",
        "label": "middle",
        "count": 2106,
        "percent": 22.27
      },
      {
        "range": "60-80%",
        "label": "late-mid",
        "count": 2446,
        "percent": 25.87
      },
      {
        "range": "80-100%",
        "label": "late",
        "count": 2281,
        "percent": 24.12
      }
    ],
    "mean_position": 0.5758,
    "std_position": 0.2587
  },
  "activation_distribution": {
    "sampling": {
      "method": "sequential_from_start",
      "description": "First N tokens in corpus order",
      "tokens_scanned": 100000,
      "n_activations": 15,
      "corpus_coverage": 0.0019
    },
    "percentiles": {
      "p10": 0.0279,
      "p25": 0.0507,
      "p50": 0.0831,
      "p75": 0.1275,
      "p90": 0.227,
      "p95": 0.2347,
      "p99": 0.2425
    },
    "skewness": 0.9179,
    "kurtosis": -0.5329,
    "min": 0.0214,
    "max": 0.2444,
    "mean": 0.1011,
    "std": 0.0727
  },
  "top_token_contexts": {
    "sampling": {
      "method": "sequential_from_start",
      "description": "First N tokens in corpus order, top activations per token",
      "tokens_scanned": 100000,
      "corpus_coverage": 0.0019,
      "activations_found": 15,
      "unique_tokens_found": 5
    },
    "tokens": [
      {
        "token": " away",
        "count": 6,
        "mean_activation": 0.1473
      },
      {
        "token": " out",
        "count": 5,
        "mean_activation": 0.0717
      },
      {
        "token": " home",
        "count": 2,
        "mean_activation": 0.0523
      },
      {
        "token": " disappeared",
        "count": 1,
        "mean_activation": 0.0266
      },
      {
        "token": " off",
        "count": 1,
        "mean_activation": 0.1427
      }
    ]
  }
}