{
  "feature_idx": 15889,
  "stats": {
    "sampling": {
      "method": "sequential_from_start",
      "description": "First N tokens in corpus order (not random)",
      "tokens_scanned": 100000,
      "corpus_coverage": 0.0019
    },
    "total_activations": 8,
    "mean_when_active": 0.05594635009765625,
    "max_activation": 0.160400390625,
    "std_when_active": 0.04183679135815395,
    "activation_rate": 8e-05
  },
  "top_tokens": {
    "sampling": {
      "method": "sequential_from_start",
      "description": "First N activations in corpus order (not random)",
      "activations_collected": 6579,
      "tokens_scanned": 51702947,
      "corpus_coverage": 1.0
    },
    "top_tokens": [
      {
        "token": " space",
        "count": 2262,
        "mean_activation": 0.06357887800977254
      },
      {
        "token": "usa",
        "count": 932,
        "mean_activation": 0.16967007223628622
      },
      {
        "token": " stars",
        "count": 522,
        "mean_activation": 0.055253946004699475
      },
      {
        "token": " death",
        "count": 370,
        "mean_activation": 0.06283000224345439
      },
      {
        "token": " coma",
        "count": 276,
        "mean_activation": 0.11197596010954483
      },
      {
        "token": " disaster",
        "count": 205,
        "mean_activation": 0.03830112364233994
      },
      {
        "token": "us",
        "count": 173,
        "mean_activation": 0.026730223198157516
      },
      {
        "token": " USA",
        "count": 164,
        "mean_activation": 0.04803764529344512
      },
      {
        "token": " science",
        "count": 121,
        "mean_activation": 0.07427247102595558
      },
      {
        "token": " Space",
        "count": 65,
        "mean_activation": 0.09631911057692308
      }
    ]
  },
  "top_activations": {
    "sampling": {
      "method": "top_by_activation",
      "description": "Strongest activations within scanned tokens (not full corpus)",
      "top_k_requested": 10,
      "n_found": 10,
      "activations_scanned": 6579,
      "tokens_scanned": 51702947,
      "corpus_coverage": 1.0
    },
    "activations": [
      {
        "context": "... pork/cheese/bean pup**usa**. I'm taking credit fo...",
        "active_token": "usa",
        "activation": 0.22265625,
        "review_id": "PlnNpGIQD5Lh0GUuJyKDAA",
        "position": 116
      },
      {
        "context": "...nd then serve, my pup**usa** was cold and they cha...",
        "active_token": "usa",
        "activation": 0.2203369140625,
        "review_id": "JEtl45tmbYHWYQZKNSOQWg",
        "position": 38
      },
      {
        "context": "...n tamale, a mixed pup**usa** and an order of tinga...",
        "active_token": "usa",
        "activation": 0.219970703125,
        "review_id": "qt0lERKPNSxyEGUyhjWqRQ",
        "position": 96
      },
      {
        "context": "...nly a $1.75 for a pup**usa**?  Sign me up!  And th...",
        "active_token": "usa",
        "activation": 0.2197265625,
        "review_id": "hWEwOHY71WmiiEAllJ08VQ",
        "position": 171
      },
      {
        "context": "...n burrito and the pup**usa** with queso, pork, and...",
        "active_token": "usa",
        "activation": 0.21728515625,
        "review_id": "w3b7T6wQsjZLNeY104jkGA",
        "position": 71
      },
      {
        "context": "...ido to put on the pup**usa**, they might make thes...",
        "active_token": "usa",
        "activation": 0.217041015625,
        "review_id": "E_I8bDoETaxWa8-AcouvEA",
        "position": 302
      },
      {
        "context": "...ing almost like a pup**usa**) is the best thing of...",
        "active_token": "usa",
        "activation": 0.2164306640625,
        "review_id": "qt0HSrkYbi_FO-gmVPfqlA",
        "position": 25
      },
      {
        "context": "...a bean and cheese pup**usa** (cooks longer 10-15mi...",
        "active_token": "usa",
        "activation": 0.2159423828125,
        "review_id": "NP8rbBynjMrGHPYWBjEa1g",
        "position": 85
      },
      {
        "context": "...xt, I had a mixed pup**usa**, which was pretty sat...",
        "active_token": "usa",
        "activation": 0.2156982421875,
        "review_id": "IPRjvJoE7SooJXBkhp52wg",
        "position": 275
      },
      {
        "context": "...tada mixed with a pup**usa** in the picture (in ca...",
        "active_token": "usa",
        "activation": 0.2142333984375,
        "review_id": "EiEJXHMN9ReTFSscqVWzIQ",
        "position": 238
      }
    ]
  },
  "ngram_analysis": {
    "feature_idx": 15889,
    "sampling": {
      "method": "top_by_activation",
      "description": "Top N activations by strength (not random)",
      "n_requested": 500,
      "n_found": 500,
      "tokens_scanned": 51702947,
      "corpus_coverage": 1.0,
      "activation_range": {
        "min": 0.1725,
        "max": 0.2227,
        "mean": 0.1905
      }
    },
    "n_contexts_analyzed": 500,
    "context_window": 5,
    "ngrams": {
      "2grams": [
        {
          "ngram": [
            " pup",
            "usa"
          ],
          "ngram_str": " pupusa",
          "count": 472,
          "percent": 94.4
        },
        {
          "ngram": [
            " a",
            " pup"
          ],
          "ngram_str": " a pup",
          "count": 94,
          "percent": 18.8
        },
        {
          "ngram": [
            " the",
            " pup"
          ],
          "ngram_str": " the pup",
          "count": 83,
          "percent": 16.6
        },
        {
          "ngram": [
            "usa",
            "."
          ],
          "ngram_str": "usa.",
          "count": 73,
          "percent": 14.6
        },
        {
          "ngram": [
            "usa",
            ","
          ],
          "ngram_str": "usa,",
          "count": 64,
          "percent": 12.8
        },
        {
          "ngram": [
            "usa",
            " and"
          ],
          "ngram_str": "usa and",
          "count": 60,
          "percent": 12.0
        },
        {
          "ngram": [
            " cheese",
            " pup"
          ],
          "ngram_str": " cheese pup",
          "count": 57,
          "percent": 11.4
        },
        {
          "ngram": [
            "\u00c4",
            "\u012c"
          ],
          "ngram_str": "\u00c4\u012c",
          "count": 52,
          "percent": 10.4
        },
        {
          "ngram": [
            " and",
            " cheese"
          ],
          "ngram_str": " and cheese",
          "count": 39,
          "percent": 7.8
        },
        {
          "ngram": [
            ".",
            " The"
          ],
          "ngram_str": ". The",
          "count": 37,
          "percent": 7.4
        },
        {
          "ngram": [
            " and",
            " a"
          ],
          "ngram_str": " and a",
          "count": 36,
          "percent": 7.2
        },
        {
          "ngram": [
            ",",
            " and"
          ],
          "ngram_str": ", and",
          "count": 36,
          "percent": 7.2
        },
        {
          "ngram": [
            "usa",
            " was"
          ],
          "ngram_str": "usa was",
          "count": 30,
          "percent": 6.0
        },
        {
          "ngram": [
            ".",
            " "
          ],
          "ngram_str": ". ",
          "count": 25,
          "percent": 5.0
        },
        {
          "ngram": [
            "up",
            "usa"
          ],
          "ngram_str": "upusa",
          "count": 22,
          "percent": 4.4
        }
      ],
      "3grams": [
        {
          "ngram": [
            " a",
            " pup",
            "usa"
          ],
          "ngram_str": " a pupusa",
          "count": 93,
          "percent": 18.6
        },
        {
          "ngram": [
            " the",
            " pup",
            "usa"
          ],
          "ngram_str": " the pupusa",
          "count": 83,
          "percent": 16.6
        },
        {
          "ngram": [
            " pup",
            "usa",
            "."
          ],
          "ngram_str": " pupusa.",
          "count": 70,
          "percent": 14.0
        },
        {
          "ngram": [
            " pup",
            "usa",
            ","
          ],
          "ngram_str": " pupusa,",
          "count": 63,
          "percent": 12.6
        },
        {
          "ngram": [
            " pup",
            "usa",
            " and"
          ],
          "ngram_str": " pupusa and",
          "count": 55,
          "percent": 11.0
        },
        {
          "ngram": [
            " cheese",
            " pup",
            "usa"
          ],
          "ngram_str": " cheese pupusa",
          "count": 55,
          "percent": 11.0
        },
        {
          "ngram": [
            " and",
            " cheese",
            " pup"
          ],
          "ngram_str": " and cheese pup",
          "count": 35,
          "percent": 7.0
        },
        {
          "ngram": [
            " pup",
            "usa",
            " was"
          ],
          "ngram_str": " pupusa was",
          "count": 30,
          "percent": 6.0
        },
        {
          "ngram": [
            "\u012c",
            "\u00c4",
            "\u012c"
          ],
          "ngram_str": "\u012c\u00c4\u012c",
          "count": 19,
          "percent": 3.8
        },
        {
          "ngram": [
            " The",
            " pup",
            "usa"
          ],
          "ngram_str": " The pupusa",
          "count": 19,
          "percent": 3.8
        },
        {
          "ngram": [
            " pup",
            "usa",
            "'s"
          ],
          "ngram_str": " pupusa's",
          "count": 15,
          "percent": 3.0
        },
        {
          "ngram": [
            " had",
            " a",
            " pup"
          ],
          "ngram_str": " had a pup",
          "count": 15,
          "percent": 3.0
        },
        {
          "ngram": [
            " pup",
            "usa",
            " is"
          ],
          "ngram_str": " pupusa is",
          "count": 15,
          "percent": 3.0
        },
        {
          "ngram": [
            "usa",
            ".",
            " The"
          ],
          "ngram_str": "usa. The",
          "count": 14,
          "percent": 2.8
        },
        {
          "ngram": [
            " and",
            " pup",
            "usa"
          ],
          "ngram_str": " and pupusa",
          "count": 14,
          "percent": 2.8
        }
      ],
      "4grams": [
        {
          "ngram": [
            " and",
            " cheese",
            " pup",
            "usa"
          ],
          "ngram_str": " and cheese pupusa",
          "count": 34,
          "percent": 6.8
        },
        {
          "ngram": [
            " a",
            " pup",
            "usa",
            ","
          ],
          "ngram_str": " a pupusa,",
          "count": 18,
          "percent": 3.6
        },
        {
          "ngram": [
            " cheese",
            " pup",
            "usa",
            " and"
          ],
          "ngram_str": " cheese pupusa and",
          "count": 16,
          "percent": 3.2
        },
        {
          "ngram": [
            " cheese",
            " pup",
            "usa",
            ","
          ],
          "ngram_str": " cheese pupusa,",
          "count": 15,
          "percent": 3.0
        },
        {
          "ngram": [
            " had",
            " a",
            " pup",
            "usa"
          ],
          "ngram_str": " had a pupusa",
          "count": 15,
          "percent": 3.0
        },
        {
          "ngram": [
            " a",
            " pup",
            "usa",
            "."
          ],
          "ngram_str": " a pupusa.",
          "count": 14,
          "percent": 2.8
        },
        {
          "ngram": [
            " pup",
            "usa",
            ".",
            " The"
          ],
          "ngram_str": " pupusa. The",
          "count": 14,
          "percent": 2.8
        },
        {
          "ngram": [
            " and",
            " a",
            " pup",
            "usa"
          ],
          "ngram_str": " and a pupusa",
          "count": 13,
          "percent": 2.6
        },
        {
          "ngram": [
            ".",
            " The",
            " pup",
            "usa"
          ],
          "ngram_str": ". The pupusa",
          "count": 13,
          "percent": 2.6
        },
        {
          "ngram": [
            " the",
            " pup",
            "usa",
            ","
          ],
          "ngram_str": " the pupusa,",
          "count": 11,
          "percent": 2.2
        },
        {
          "ngram": [
            " the",
            " pup",
            "usa",
            "."
          ],
          "ngram_str": " the pupusa.",
          "count": 11,
          "percent": 2.2
        },
        {
          "ngram": [
            " pup",
            "usa",
            " and",
            " a"
          ],
          "ngram_str": " pupusa and a",
          "count": 11,
          "percent": 2.2
        },
        {
          "ngram": [
            "\u00c4",
            "\u012c",
            "\u00c4",
            "\u012c"
          ],
          "ngram_str": "\u00c4\u012c\u00c4\u012c",
          "count": 11,
          "percent": 2.2
        },
        {
          "ngram": [
            " pup",
            "usa",
            ".",
            " "
          ],
          "ngram_str": " pupusa. ",
          "count": 11,
          "percent": 2.2
        },
        {
          "ngram": [
            " bean",
            " and",
            " cheese",
            " pup"
          ],
          "ngram_str": " bean and cheese pup",
          "count": 10,
          "percent": 2.0
        }
      ]
    }
  },
  "coactivation": {
    "sampling": {
      "method": "sequential_from_start",
      "description": "First N activations in corpus order",
      "activations_sampled": 6579,
      "tokens_scanned": 51702947,
      "corpus_coverage": 1.0
    },
    "coactivated_features": [
      {
        "feature_idx": 17175,
        "count": 4376,
        "percent": 66.51
      },
      {
        "feature_idx": 12189,
        "count": 2550,
        "percent": 38.76
      },
      {
        "feature_idx": 1227,
        "count": 2458,
        "percent": 37.36
      },
      {
        "feature_idx": 18704,
        "count": 2420,
        "percent": 36.78
      },
      {
        "feature_idx": 13985,
        "count": 2383,
        "percent": 36.22
      },
      {
        "feature_idx": 1318,
        "count": 2382,
        "percent": 36.21
      },
      {
        "feature_idx": 9115,
        "count": 2375,
        "percent": 36.1
      },
      {
        "feature_idx": 7843,
        "count": 2361,
        "percent": 35.89
      },
      {
        "feature_idx": 21504,
        "count": 2331,
        "percent": 35.43
      },
      {
        "feature_idx": 22001,
        "count": 2243,
        "percent": 34.09
      },
      {
        "feature_idx": 3574,
        "count": 2228,
        "percent": 33.87
      },
      {
        "feature_idx": 22894,
        "count": 1634,
        "percent": 24.84
      },
      {
        "feature_idx": 20172,
        "count": 1604,
        "percent": 24.38
      },
      {
        "feature_idx": 1390,
        "count": 1488,
        "percent": 22.62
      },
      {
        "feature_idx": 1938,
        "count": 1472,
        "percent": 22.37
      },
      {
        "feature_idx": 11584,
        "count": 1409,
        "percent": 21.42
      },
      {
        "feature_idx": 21958,
        "count": 1392,
        "percent": 21.16
      },
      {
        "feature_idx": 5196,
        "count": 1346,
        "percent": 20.46
      },
      {
        "feature_idx": 11491,
        "count": 1317,
        "percent": 20.02
      },
      {
        "feature_idx": 3953,
        "count": 1281,
        "percent": 19.47
      }
    ]
  },
  "position_distribution": {
    "sampling": {
      "method": "sequential_from_start",
      "description": "First N activations in corpus order",
      "activations_sampled": 6579,
      "tokens_scanned": 51702947,
      "corpus_coverage": 1.0
    },
    "bins": [
      {
        "range": "0-20%",
        "label": "early",
        "count": 1900,
        "percent": 28.88
      },
      {
        "range": "20-40%",
        "label": "early-mid",
        "count": 1218,
        "percent": 18.51
      },
      {
        "range": "40-60%",
        "label": "middle",
        "count": 1089,
        "percent": 16.55
      },
      {
        "range": "60-80%",
        "label": "late-mid",
        "count": 1092,
        "percent": 16.6
      },
      {
        "range": "80-100%",
        "label": "late",
        "count": 1280,
        "percent": 19.46
      }
    ],
    "mean_position": 0.4563,
    "std_position": 0.3109
  },
  "activation_distribution": {
    "sampling": {
      "method": "sequential_from_start",
      "description": "First N tokens in corpus order",
      "tokens_scanned": 100000,
      "n_activations": 8,
      "corpus_coverage": 0.0019
    },
    "percentiles": {
      "p10": 0.0269,
      "p25": 0.0304,
      "p50": 0.0419,
      "p75": 0.0598,
      "p90": 0.0929,
      "p95": 0.1266,
      "p99": 0.1536
    },
    "skewness": 1.7994,
    "kurtosis": 1.9627,
    "min": 0.0206,
    "max": 0.1604,
    "mean": 0.0559,
    "std": 0.0418
  },
  "top_token_contexts": {
    "sampling": {
      "method": "sequential_from_start",
      "description": "First N tokens in corpus order, top activations per token",
      "tokens_scanned": 100000,
      "corpus_coverage": 0.0019,
      "activations_found": 8,
      "unique_tokens_found": 6
    },
    "tokens": [
      {
        "token": " space",
        "count": 3,
        "mean_activation": 0.0702
      },
      {
        "token": "ami",
        "count": 1,
        "mean_activation": 0.0471
      },
      {
        "token": " disaster",
        "count": 1,
        "mean_activation": 0.0368
      },
      {
        "token": " stars",
        "count": 1,
        "mean_activation": 0.0583
      },
      {
        "token": " industrial",
        "count": 1,
        "mean_activation": 0.0307
      },
      {
        "token": " death",
        "count": 1,
        "mean_activation": 0.064
      }
    ]
  }
}